{
  "patient_name": "Phạm Tuấn Hưng",
  "phone": "0336018126",
  "customer_id": "CUS-3bc6fb07db",
  "doctor_name": "BS. Lê Khánh",
  "appointment_time": "2025-08-23 17:00",
  "room": "TMH.201",
  "queue_number": "A-051",
  "symptoms": [
    {
      "name": "Ho",
      "severity": null,
      "duration": "2 ngày"
    },
    {
      "name": "Sổ mũi",
      "severity": null,
      "duration": "2 ngày"
    }
  ],
  "tentative_diagnoses": [
    "Viêm đường hô hấp trên"
  ],
  "tests_recommended": [],
  "medications_advised": [],
  "diet_notes": "Uống nhiều nước ấm, ăn thức ăn mềm, dễ tiêu, bổ sung vitamin C để tăng cường sức đề kháng.",
  "follow_up": "Tái khám theo lịch hẹn hoặc khi triệu chứng không thuyên giảm.",
  "warnings": "Đến ngay cơ sở y tế gần nhất nếu có dấu hiệu khó thở, sốt cao không hạ, hoặc ho kéo dài."
}